setup.py
CSFunctions/__init__.py
CSFunctions.egg-info/PKG-INFO
CSFunctions.egg-info/SOURCES.txt
CSFunctions.egg-info/dependency_links.txt
CSFunctions.egg-info/requires.txt
CSFunctions.egg-info/top_level.txt